diPLSlib/__init__.py
diPLSlib/functions.py
diPLSlib/models.py
diPLSlib/utils/__init__.py
diPLSlib/utils/misc.py
diplslib-2.5.0.dist-info/licenses/LICENSE
diplslib-2.5.0.dist-info/METADATA
diplslib-2.5.0.dist-info/WHEEL
diplslib-2.5.0.dist-info/top_level.txt
diplslib-2.5.0.dist-info/RECORD
