Metadata-Version: 2.4
Name: diPLSlib
Version: 2.5.0
Summary: Python package for domain adaptation in multivariate regression
Home-page: https://github.com/B-Analytics/di-PLS
Author: Ramin Nikzad-Langerodi
Author-email: ramin.nikzad-langerodi@scch.at
Classifier: Programming Language :: Python :: 3
Classifier: License :: OSI Approved :: GNU General Public License v3 (GPLv3)
Classifier: Operating System :: OS Independent
Requires-Python: >=3.6
License-File: LICENSE
Requires-Dist: numpy
Requires-Dist: matplotlib
Requires-Dist: scipy
Requires-Dist: scikit-learn
Dynamic: author
Dynamic: author-email
Dynamic: classifier
Dynamic: description
Dynamic: description-content-type
Dynamic: home-page
Dynamic: license-file
Dynamic: requires-dist
Dynamic: requires-python
Dynamic: summary
